__init__.py
agent.py
cli.py
utils.py
config/.rokovoignore
config/rokovo.toml
config/rokovo_context.md
prompts/faq_system.j2
prompts/faq_user.j2
prompts/interactive_qa.j2
rokovo-0.2.3.dist-info/METADATA
rokovo-0.2.3.dist-info/WHEEL
rokovo-0.2.3.dist-info/entry_points.txt
rokovo-0.2.3.dist-info/licenses/LICENSE
rokovo-0.2.3.dist-info/RECORD
