Metadata-Version: 2.4
Name: rokovo
Version: 0.2.3
Summary: Rokovo CLI
Project-URL: Homepage, https://rokovo.io
Project-URL: Repository, https://github.com/dezh-tech/rokovo-cli
Project-URL: Issues, https://github.com/dezh-tech/rokovo-cli/issues
Author-email: Rokovo <info@rokovo.io>
License: MIT
License-File: LICENSE
Keywords: agents,ai,ai-agents,cli,langchain,rokovo
Classifier: Development Status :: 3 - Alpha
Classifier: Environment :: Console
Classifier: Intended Audience :: Developers
Classifier: License :: OSI Approved :: MIT License
Classifier: Programming Language :: Python
Classifier: Programming Language :: Python :: 3
Classifier: Programming Language :: Python :: 3 :: Only
Classifier: Programming Language :: Python :: 3.9
Classifier: Programming Language :: Python :: 3.10
Classifier: Programming Language :: Python :: 3.11
Classifier: Programming Language :: Python :: 3.12
Classifier: Topic :: Software Development :: Libraries :: Python Modules
Requires-Python: >=3.10
Requires-Dist: chromadb
Requires-Dist: jinja2
Requires-Dist: langchain
Requires-Dist: langchain-chroma
Requires-Dist: langchain-community
Requires-Dist: langchain-core
Requires-Dist: langchain-huggingface
Requires-Dist: langchain-openai
Requires-Dist: sentence-transformers
Requires-Dist: tomli>=1.1.0; python_version < '3.11'
Requires-Dist: typer
Requires-Dist: xdg-base-dirs
Provides-Extra: dev
Requires-Dist: build>=1.2.1; extra == 'dev'
Requires-Dist: ruff>=0.4.2; extra == 'dev'
Requires-Dist: twine>=5.1.1; extra == 'dev'
